{
    "singlePage": [],
    "startSite": "index.html",
    "filingNum": "",
    "onePageListNum": 15,
    "commentLabelColor": "#006b75",
    "yearColorList": ["#bc4c00", "#0969da", "#1f883d", "#A333D0"],
    "i18n": "CN",
    "themeMode": "manual",
    "dayTheme": "light",
    "nightTheme": "dark",
    "urlMode": "pinyin",
    "script": "<!-- 引入官网所需JS，匹配页面交互功能 -->\n<script src=\"assets/js/jquery.min.js\"></script>\n<script src=\"assets/js/jquery.scrolly.min.js\"></script>\n<script src=\"assets/js/jquery.scrollex.min.js\"></script>\n<script src=\"assets/js/browser.min.js\"></script>\n<script src=\"assets/js/breakpoints.min.js\"></script>\n<script src=\"assets/js/util.js\"></script>\n<script src=\"assets/js/main.js\"></script>",
    "style": "<!-- 引入官网主CSS，统一页面风格 -->\n<link rel=\"stylesheet\" href=\"assets/css/main.css\" />\n<noscript><link rel=\"stylesheet\" href=\"assets/css/noscript.css\" /></noscript>",
    "head": "<!-- 官网头部元信息，匹配SEO与验证需求 -->\n<meta name=\"baidu-site-verification\" content=\"codeva-GoGsXK3SLW\" />\n<meta name=\"viewport\" content=\"width=device-width, initial-scale=1, user-scalable=no\" />\n<meta name=\"description\" content=\"北京愉佚科技发展有限公司致力于科技推广和应用服务业，提供全面的技术支持和服务。\" />\n<meta name=\"keywords\" content=\"北京愉佚科技, 技术服务, 创新, 科技推广\" />",
    "indexScript": "",
    "indexStyle": "",
    "bottomText": "<!-- 页脚版权信息，匹配官网格式 -->\n<footer id=\"footer\">\n    <div class=\"inner\">\n        <ul class=\"copyright\">\n            <li>&copy; 北京愉佚科技发展有限公司 2025</li>\n            <li>&copy; PleasantTech Ventures Co., Ltd. 2025</li>\n        </ul>\n    </div>\n</footer>",
    "showPostSource": 0,
    "iconList": {
        "首页": "index.html",
        "公司简介": "about.html",
        "服务项目": "services.html",
        "新闻动态": "https://space.bilibili.com/3546822953928942?spm_id_from=333.33.0.0",
        "招聘信息": "careers.html",
        "联系方式": "contact.html",
        "英文版本": "index_en.html"
    },
    "UTC": 8,
    "rssSplit": "sentence",
    "exlink": {
        "https://space.bilibili.com/3546822953928942?spm_id_from=333.33.0.0": {
            "target": "_blank",
            "title": "新闻动态（跳转至B站）"
        },
        "index_en.html": {
            "title": "切换至英文版本"
        }
    },
    "needComment": 0,
    "allHead": "",
    "title": "北京愉佚科技发展有限公司",
    "subTitle": "致力于科技推广和应用服务业，提供全面的技术支持和服务",
    "avatarUrl": "image/logo.png",
    "GMEEK_VERSION": "last",
    "postListJson": {
        "P1": {
            "htmlDir": "docs/post/CN_test-zhong-wen-jie-mian-ce-shi.html",
            "labels": ["公司动态"],
            "postTitle": "CN_test中文界面测试",
            "postUrl": "post/CN_test-zhong-wen-jie-mian-ce-shi.html",
            "postSourceUrl": "https://github.com/GeorgeQii/Company_blog_CN.github.io/issues/1",
            "commentNum": 0,
            "wordCount": 4,
            "description": "中文界面测试内容，用于验证官网风格适配。",
            "top": 0,
            "createdAt": 1758172102,
            "style": "",
            "script": "",
            "head": "",
            "ogImage": "image/logo.png",
            "createdDate": "2025-09-18",
            "dateLabelColor": "#0969da"
        },
        "P2": {
            "htmlDir": "docs/post/uyfyg.html",
            "labels": ["服务介绍"],
            "postTitle": "技术服务能力展示",
            "postUrl": "post/uyfyg.html",
            "postSourceUrl": "https://github.com/GeorgeQii/Company_blog_CN.github.io/issues/2",
            "commentNum": 0,
            "wordCount": 7,
            "description": "介绍北京愉佚科技核心技术服务，含政企数字化、社区解决方案。",
            "top": 0,
            "createdAt": 1758172310,
            "style": "",
            "script": "",
            "head": "",
            "ogImage": "image/logo.png",
            "createdDate": "2025-09-18",
            "dateLabelColor": "#0969da"
        },
        "P3": {
            "htmlDir": "docs/post/cdawd.html",
            "labels": ["行业资讯"],
            "postTitle": "科技推广行业动态",
            "postUrl": "post/cdawd.html",
            "postSourceUrl": "https://github.com/GeorgeQii/Company_blog_CN.github.io/issues/3",
            "commentNum": 0,
            "wordCount": 8,
            "description": "分享科技推广与应用服务行业最新政策及市场动态。",
            "top": 0,
            "createdAt": 1758173554,
            "style": "",
            "script": "",
            "head": "",
            "ogImage": "image/logo.png",
            "createdDate": "2025-09-18",
            "dateLabelColor": "#0969da"
        }
    },
    "singeListJson": {},
    "labelColorDict": {
        "bug": "#d73a4a",
        "documentation": "#0075ca",
        "duplicate": "#cfd3d7",
        "enhancement": "#a2eeef",
        "good first issue": "#7057ff",
        "help wanted": "#008672",
        "invalid": "#e4e669",
        "question": "#d876e3",
        "wontfix": "#ffffff",
        "公司动态": "#0969da",
        "服务介绍": "#1f883d",
        "行业资讯": "#bc4c00"
    },
    "displayTitle": "北京愉佚科技发展有限公司",
    "faviconUrl": "image/logo.png",
    "ogImage": "image/logo.png",
    "primerCSS": "",
    "homeUrl": "https://GeorgeQii.github.io/Company_blog_CN.github.io",
    "prevUrl": "disabled",
    "nextUrl": "disabled"
}
